setup.py
pyNovelist.egg-info/PKG-INFO
pyNovelist.egg-info/SOURCES.txt
pyNovelist.egg-info/dependency_links.txt
pyNovelist.egg-info/requires.txt
pyNovelist.egg-info/top_level.txt
pynovelist/beat_generator.py
pynovelist/character_generator.py
pynovelist/cli_interface.py
pynovelist/config.py
pynovelist/content_generator.py
pynovelist/outline_generator.py
pynovelist/persistence.py
pynovelist/post_processing.py
pynovelist/synopsis_generator.py
pynovelist/user_input.py